yippy/__init__.py
yippy/_version.py
yippy/coronagraph.py
yippy/header.py
yippy/jax_funcs.py
yippy/logger.py
yippy/offax.py
yippy/offjax.py
yippy/sky_trans.py
yippy/stellar_intens.py
yippy/util.py
yippy-1.10.0.dist-info/METADATA
yippy-1.10.0.dist-info/WHEEL
yippy-1.10.0.dist-info/licenses/LICENSE
yippy-1.10.0.dist-info/RECORD
